Workbook

Sheet 📊 Dashboard
A1: FinTrack Pro · Freelancer Finance Dashboard
A2: Auto-calculated from data in other sheets · Do not edit this sheet directly
A9: NET SAVINGS (Income − Expenses − Invested + Withdrawals) | E9: =IFERROR(SUM('💰 Income'!F:F)-SUM('💸 Expenses'!F:F)-SUM('📈 Investments'!D:D)+SUM('🏧 Withdrawals'!D:D),0)
A11: ⚠ UNPAID WORK (from Ledger)
A12: Total Unpaid Amount: | E12: =IFERROR(SUMIF('📋 Ledger'!H:H,"Unpaid",'📋 Ledger'!E:E),0)
A44: TOTAL INCOME | C44: TOTAL EXPENSES | E44: INVESTED | G44: ASSETS VALUE
A45: =IFERROR(SUM('💰 Income'!F:F),0) | C45: =IFERROR(SUM('💸 Expenses'!F:F),0) | E45: =IFERROR(SUM('📈 Investments'!D:D),0) | G45: =IFERROR(SUMPRODUCT('🏆 Assets'!D:D*'🏆 Assets'!G:G),0)
A46: All-time income | C46: All-time expenses | E46: Total invested | G46: Current asset value

Sheet 💰 Income
A1: 💰 Income Log
A2: Record every payment received — from clients, family, or any source
A4: # | B4: Date | C4: From Whom | D4: Category | E4: Payment Method | F4: Amount (₹) | G4: Notes
A5: =IFERROR(ROW()-4,"")
A6: =IFERROR(ROW()-4,"")
A7: =IFERROR(ROW()-4,"")
A8: =IFERROR(ROW()-4,"")
A9: =IFERROR(ROW()-4,"")
A10: =IFERROR(ROW()-4,"")
A11: =IFERROR(ROW()-4,"")
A12: =IFERROR(ROW()-4,"")
A13: =IFERROR(ROW()-4,"")
A14: =IFERROR(ROW()-4,"")
A15: =IFERROR(ROW()-4,"")
A16: =IFERROR(ROW()-4,"")
... A204: =IFERROR(ROW()-4,"")
E205: TOTAL | F205: =SUM(F5:F204)

Sheet 💸 Expenses
A1: 💸 Expense Log
A2: Track every penny you spend — method, category, and notes
A4: # | B4: Date | C4: Description | D4: Category | E4: Payment Method | F4: Card Last 4 | G4: Amount (₹) | H4: Notes
A5: =IFERROR(ROW()-4,"")
A6: =IFERROR(ROW()-4,"")
A7: =IFERROR(ROW()-4,"")
A8: =IFERROR(ROW()-4,"")
A9: =IFERROR(ROW()-4,"")
A10: =IFERROR(ROW()-4,"")
A11: =IFERROR(ROW()-4,"")
A12: =IFERROR(ROW()-4,"")
A13: =IFERROR(ROW()-4,"")
A14: =IFERROR(ROW()-4,"")
A15: =IFERROR(ROW()-4,"")
A16: =IFERROR(ROW()-4,"")
... A204: =IFERROR(ROW()-4,"")
F205: TOTAL | G205: =SUM(G5:G204)

Sheet 👤 Clients
A1: 👤 Clients
A2: Master list of all clients — referenced by the Ledger sheet
A4: Client ID | B4: Client Name | C4: Phone | D4: Email | E4: Address | F4: GSTIN | G4: Notes
A5: =IFERROR("CLT-"&TEXT(ROW()-4,"000"),"")
A6: =IFERROR("CLT-"&TEXT(ROW()-4,"000"),"")
A7: =IFERROR("CLT-"&TEXT(ROW()-4,"000"),"")
A8: =IFERROR("CLT-"&TEXT(ROW()-4,"000"),"")
A9: =IFERROR("CLT-"&TEXT(ROW()-4,"000"),"")
A10: =IFERROR("CLT-"&TEXT(ROW()-4,"000"),"")
A11: =IFERROR("CLT-"&TEXT(ROW()-4,"000"),"")
A12: =IFERROR("CLT-"&TEXT(ROW()-4,"000"),"")
A13: =IFERROR("CLT-"&TEXT(ROW()-4,"000"),"")
A14: =IFERROR("CLT-"&TEXT(ROW()-4,"000"),"")
A15: =IFERROR("CLT-"&TEXT(ROW()-4,"000"),"")
A16: =IFERROR("CLT-"&TEXT(ROW()-4,"000"),"")
... A104: =IFERROR("CLT-"&TEXT(ROW()-4,"000"),"")

Sheet 📋 Ledger
A1: 📋 Client Ledger
A2: Work log — every task, its price, invoice no., and payment status
A4: # | B4: Date | C4: Client Name | D4: Work Detail | E4: Price (₹) | F4: Invoice No. | G4: Status | H4: Paid Date | I4: Payment Method | J4: Notes
A5: =IFERROR(ROW()-4,"")
A6: =IFERROR(ROW()-4,"")
A7: =IFERROR(ROW()-4,"")
A8: =IFERROR(ROW()-4,"")
A9: =IFERROR(ROW()-4,"")
A10: =IFERROR(ROW()-4,"")
A11: =IFERROR(ROW()-4,"")
A12: =IFERROR(ROW()-4,"")
A13: =IFERROR(ROW()-4,"")
A14: =IFERROR(ROW()-4,"")
A15: =IFERROR(ROW()-4,"")
A16: =IFERROR(ROW()-4,"")
... A304: =IFERROR(ROW()-4,"")
D305: TOTAL BILLED | E305: =SUM(E5:E304)
D306: TOTAL UNPAID | E306: =SUMIF(G5:G304,"Unpaid",E5:E304)

Sheet 🧾 Invoices
A1: 🧾 Invoice Log
A2: Track every invoice generated — linked to ledger entries
A4: Invoice No. | B4: Invoice Date | C4: Client Name | D4: Total Amount (₹) | E4: Status | F4: Due Date | G4: Payment Date | H4: Payment Method | I4: Notes

Sheet 🏆 Assets
A1: 🏆 Assets
A2: Track physical & financial assets — gold, silver, property, electronics…
A4: # | B4: Asset Name | C4: Type | D4: Quantity | E4: Unit | F4: Buy Price/Unit (₹) | G4: Buy Date | H4: Current Price/Unit (₹) | I4: Buy Value (₹) | J4: Current Value (₹) | K4: Gain/Loss (₹) | L4: Gain % | M4: Notes
A5: =IFERROR(ROW()-4,"") | I5: =IFERROR(D5*F5,0) | J5: =IFERROR(D5*H5,0) | K5: =IFERROR(J5-I5,0) | L5: =IFERROR((J5-I5)/I5,0)
A6: =IFERROR(ROW()-4,"") | I6: =IFERROR(D6*F6,0) | J6: =IFERROR(D6*H6,0) | K6: =IFERROR(J6-I6,0) | L6: =IFERROR((J6-I6)/I6,0)
A7: =IFERROR(ROW()-4,"") | I7: =IFERROR(D7*F7,0) | J7: =IFERROR(D7*H7,0) | K7: =IFERROR(J7-I7,0) | L7: =IFERROR((J7-I7)/I7,0)
A8: =IFERROR(ROW()-4,"") | I8: =IFERROR(D8*F8,0) | J8: =IFERROR(D8*H8,0) | K8: =IFERROR(J8-I8,0) | L8: =IFERROR((J8-I8)/I8,0)
A9: =IFERROR(ROW()-4,"") | I9: =IFERROR(D9*F9,0) | J9: =IFERROR(D9*H9,0) | K9: =IFERROR(J9-I9,0) | L9: =IFERROR((J9-I9)/I9,0)
A10: =IFERROR(ROW()-4,"") | I10: =IFERROR(D10*F10,0) | J10: =IFERROR(D10*H10,0) | K10: =IFERROR(J10-I10,0) | L10: =IFERROR((J10-I10)/I10,0)
A11: =IFERROR(ROW()-4,"") | I11: =IFERROR(D11*F11,0) | J11: =IFERROR(D11*H11,0) | K11: =IFERROR(J11-I11,0) | L11: =IFERROR((J11-I11)/I11,0)
A12: =IFERROR(ROW()-4,"") | I12: =IFERROR(D12*F12,0) | J12: =IFERROR(D12*H12,0) | K12: =IFERROR(J12-I12,0) | L12: =IFERROR((J12-I12)/I12,0)
A13: =IFERROR(ROW()-4,"") | I13: =IFERROR(D13*F13,0) | J13: =IFERROR(D13*H13,0) | K13: =IFERROR(J13-I13,0) | L13: =IFERROR((J13-I13)/I13,0)
A14: =IFERROR(ROW()-4,"") | I14: =IFERROR(D14*F14,0) | J14: =IFERROR(D14*H14,0) | K14: =IFERROR(J14-I14,0) | L14: =IFERROR((J14-I14)/I14,0)
A15: =IFERROR(ROW()-4,"") | I15: =IFERROR(D15*F15,0) | J15: =IFERROR(D15*H15,0) | K15: =IFERROR(J15-I15,0) | L15: =IFERROR((J15-I15)/I15,0)
A16: =IFERROR(ROW()-4,"") | I16: =IFERROR(D16*F16,0) | J16: =IFERROR(D16*H16,0) | K16: =IFERROR(J16-I16,0) | L16: =IFERROR((J16-I16)/I16,0)
... A54: =IFERROR(ROW()-4,"") | I54: =IFERROR(D54*F54,0) | J54: =IFERROR(D54*H54,0) | K54: =IFERROR(J54-I54,0) | L54: =IFERROR((J54-I54)/I54,0)
H55: TOTALS | I55: =SUM(I5:I54) | J55: =SUM(J5:J54) | K55: =J55-I55

Sheet 📈 Investments
A1: 📈 Investments
A2: Mutual funds, stocks, FDs, PPF, NPS, crypto and more
A4: # | B4: Date | C4: Platform / Fund | D4: Type | E4: Amount Invested (₹) | F4: Current Value (₹) | G4: Gain/Loss (₹) | H4: Gain % | I4: Notes
A5: =IFERROR(ROW()-4,"") | G5: =IFERROR(F5-E5,0) | H5: =IFERROR((F5-E5)/E5,0)
A6: =IFERROR(ROW()-4,"") | G6: =IFERROR(F6-E6,0) | H6: =IFERROR((F6-E6)/E6,0)
A7: =IFERROR(ROW()-4,"") | G7: =IFERROR(F7-E7,0) | H7: =IFERROR((F7-E7)/E7,0)
A8: =IFERROR(ROW()-4,"") | G8: =IFERROR(F8-E8,0) | H8: =IFERROR((F8-E8)/E8,0)
A9: =IFERROR(ROW()-4,"") | G9: =IFERROR(F9-E9,0) | H9: =IFERROR((F9-E9)/E9,0)
A10: =IFERROR(ROW()-4,"") | G10: =IFERROR(F10-E10,0) | H10: =IFERROR((F10-E10)/E10,0)
A11: =IFERROR(ROW()-4,"") | G11: =IFERROR(F11-E11,0) | H11: =IFERROR((F11-E11)/E11,0)
A12: =IFERROR(ROW()-4,"") | G12: =IFERROR(F12-E12,0) | H12: =IFERROR((F12-E12)/E12,0)
A13: =IFERROR(ROW()-4,"") | G13: =IFERROR(F13-E13,0) | H13: =IFERROR((F13-E13)/E13,0)
A14: =IFERROR(ROW()-4,"") | G14: =IFERROR(F14-E14,0) | H14: =IFERROR((F14-E14)/E14,0)
A15: =IFERROR(ROW()-4,"") | G15: =IFERROR(F15-E15,0) | H15: =IFERROR((F15-E15)/E15,0)
A16: =IFERROR(ROW()-4,"") | G16: =IFERROR(F16-E16,0) | H16: =IFERROR((F16-E16)/E16,0)
... A104: =IFERROR(ROW()-4,"") | G104: =IFERROR(F104-E104,0) | H104: =IFERROR((F104-E104)/E104,0)
D105: TOTAL INVESTED | E105: =SUM(E5:E104) | F105: =SUM(F5:F104)

Sheet 🏧 Withdrawals
A1: 🏧 Withdrawals
A2: Track every withdrawal from investments or savings
A4: # | B4: Date | C4: Platform / Fund | D4: Reason | E4: Amount (₹) | F4: Notes
A5: =IFERROR(ROW()-4,"")
A6: =IFERROR(ROW()-4,"")
A7: =IFERROR(ROW()-4,"")
A8: =IFERROR(ROW()-4,"")
A9: =IFERROR(ROW()-4,"")
A10: =IFERROR(ROW()-4,"")
A11: =IFERROR(ROW()-4,"")
A12: =IFERROR(ROW()-4,"")
A13: =IFERROR(ROW()-4,"")
A14: =IFERROR(ROW()-4,"")
A15: =IFERROR(ROW()-4,"")
A16: =IFERROR(ROW()-4,"")
... A104: =IFERROR(ROW()-4,"")
D105: TOTAL | E105: =SUM(E5:E104)

Sheet 📖 How to Use
A1: 📖 How to Use FinTrack Pro Excel
A3: STEP 1 — Set Up Clients
A4: Go to the 👤 Clients sheet and add all your clients. Each client gets an auto-ID (CLT-001, CLT-002…)
A6: STEP 2 — Log Your Work (Ledger)
A7: Go to 📋 Ledger. For each piece of work done, add a row: Date, Client Name, Work Detail, Price.
A8: Status: Set to 'Unpaid' first. When client pays, change to 'Paid' and fill Paid Date + Method.
A9: Invoice No: Leave blank until you generate an invoice. Then add the same invoice number.
A10: Multiple work items can share the same Invoice No — that's how invoices group multiple tasks.
A12: STEP 3 — Log Income
A13: Go to 💰 Income. Add every payment you receive — from 'Papa', 'Rahul Client', 'Infosys', etc.
A14: Be specific in 'From Whom' — this is your money trail.
A16: STEP 4 — Log Expenses
... A37: 🔴 Red = Unpaid / Negative / Expense
